{
  "kind": "feature_evidence_report",
  "features": [
    {
      "featureId": "feature-change-the-navigation-link-text-from-top-10-to-standings-in-the-navigation-component",
      "featureTitle": "Change the navigation link text from 'top 10' to 'Standings' in the Navigation component",
      "files": [
        "frontend/src/components/Navigation.tsx"
      ],
      "components": [
        "core-infrastructure@1.0.2",
        "shadcn-ui@1.0.0",
        "build-template-react@1.0.0",
        "initial-app@1.0.0",
        "github-export-icp-cli@1.0.0"
      ],
      "testIds": [
        "REQ-1"
      ],
      "confidence": "high"
    }
  ]
}